CHANGES.rst
MANIFEST.in
README.rst
setup.cfg
setup.py
khufu_siteview/__init__.py
khufu_siteview/templatedir.py
khufu_siteview/tests.py
khufu_siteview.egg-info/PKG-INFO
khufu_siteview.egg-info/SOURCES.txt
khufu_siteview.egg-info/dependency_links.txt
khufu_siteview.egg-info/not-zip-safe
khufu_siteview.egg-info/requires.txt
khufu_siteview.egg-info/top_level.txt
khufu_siteview/templates/listing.jinja2