Metadata-Version: 1.0
Name: khufu-siteview
Version: 0.9
Summary: Easy template-to-view support
Home-page: https://github.com/khufuproject/khufu_siteview
Author: Rocky Burt
Author-email: rocky@serverzen.com
License: BSD
Keywords: pyramid khufu
Platform: UNKNOWN
Classifier: License :: OSI Approved :: BSD License
Classifier: Programming Language :: Python
Classifier: Topic :: Internet :: WWW/HTTP :: WSGI
